[
  {
    "name": "Monad ⨀",
    "tweetUrl": "https://x.com/monad/status/1953133787891527924",
    "fullText": "gave our summer intern the linkedin login\n\nwill this be his last day? find out here: https://t.co/sqOMoc28l0 https://t.co/QW5Ga35raq",
    "formatCreatedAt": "2025-08-06 16:39:17"
  },
  {
    "name": "ricardogabriel",
    "tweetUrl": "https://x.com/richgab50/status/1953120829908095395",
    "fullText": "🚀 Real momentum in motion:\n$WKSP just hit record monthly production - 2,499 units\nNo added headcount. 23% gross margin.\nAL4 in high demand\nSOLIS &amp; COR prelaunching\nMargins up. Costs stable. Output rising.\nMarket attention growing.\nWatching this setup closely.\n\n🎯 Short-term https://t.co/d3zW2lG1ir",
    "formatCreatedAt": "2025-08-06 15:47:47"
  }
]