[
  {
    "name": "Polymarket",
    "tweetUrl": "https://x.com/Polymarket/status/1998772442370810109",
    "fullText": "🚨 NEW POLYMARKET: What will Powell say during December Press Conference today?\nhttps://t.co/KJQHD8WoRb",
    "formatCreatedAt": "2025-12-10 15:11:00"
  },
  {
    "name": "Solana",
    "tweetUrl": "https://x.com/solana/status/1998770698953879635",
    "fullText": "See you tomorrow in Abu Dhabi 🫡 https://t.co/H0S2tGZ5Wl",
    "formatCreatedAt": "2025-12-10 15:04:04"
  },
  {
    "name": "OpenBuild",
    "tweetUrl": "https://x.com/OpenBuildxyz/status/1998764344453243275",
    "fullText": "High Salary Offer → Zero Assets: The Web3 Developer's Guide to Wallet Security.\n\nNorth Korean hackers stole $2B+ in 2025 by shifting focus from protocol exploits to social engineering (fake job offers, malicious files). The biggest vulnerability is no longer the code, but the https://t.co/HETTRpXN2f",
    "formatCreatedAt": "2025-12-10 14:38:49"
  },
  {
    "name": "$SERA",
    "tweetUrl": "https://x.com/SeraCoinPlay/status/1998764137124606163",
    "fullText": "Claim $800,000 - $SERA for first 4500 🔥 \n\n$SERA will List today at 14:00 UTC on $SOLANA \n\n✅ Follow @SeraCoinPlay \n✅ RT &amp; Like\n✅ Drop your $SOL address\n\nDistribution Airdrop December 11th⏳ https://t.co/fbaIT3Hshu",
    "formatCreatedAt": "2025-12-10 14:38:00"
  },
  {
    "name": "Polymarket",
    "tweetUrl": "https://x.com/Polymarket/status/1998762375978299602",
    "fullText": "Happy FOMC Day to those who celebrate.\n\n98% chance of rate cuts.\nhttps://t.co/pKf2dNqWPn",
    "formatCreatedAt": "2025-12-10 14:31:00"
  },
  {
    "name": "Korea Coin",
    "tweetUrl": "https://x.com/KoreaxCoin/status/1998758629768560748",
    "fullText": "GIVEAWAY 5,000,000 - $USDT from KOREA COIN each will receive 350 $USDT for 2000 fastest people 🎁 \n\n- Follow @KoreaxCoin \n- RT + Like ❤️ \n- Comments $SOL address \n\nGiveaway ends December 13th ⏳ https://t.co/sB9BCYZRx7",
    "formatCreatedAt": "2025-12-10 14:16:07"
  },
  {
    "name": "Korea Coin",
    "tweetUrl": "https://x.com/KoreaxCoin/status/1998758212733120571",
    "fullText": "$KOREA x #Binance  &amp; 900,000 $USDT\ngiveaway for 5555 winner 🎁\n\nJoin now:\n1️⃣ Follow @KoreaxCoin \n2️⃣ RT &amp; Like pinned post\n3️⃣ Comments $SOL wallet address\n\nGiveaway ends december 13th &amp; distribution december 14th ⏳ https://t.co/7FAiQpOI3H",
    "formatCreatedAt": "2025-12-10 14:14:27"
  },
  {
    "name": "Monad 华语社群",
    "tweetUrl": "https://x.com/monad_zw/status/1998757708481397094",
    "fullText": "We Are So back (WASB)⸺@fluffleworld\n\n透过 @fluffleworld，只要保持专注就能赚取奖励！\n \n📲 现在已经在 App Store 上架 https://t.co/uQhBjZoGTN",
    "formatCreatedAt": "2025-12-10 14:12:27"
  },
  {
    "name": "Polymarket",
    "tweetUrl": "https://x.com/Polymarket/status/1998757191113949373",
    "fullText": "JUST IN: Tourists visiting U.S. will have to submit 5 years of their social media history under new proposal.",
    "formatCreatedAt": "2025-12-10 14:10:24"
  },
  {
    "name": "Mina Protocol (httpz) 🪶",
    "tweetUrl": "https://x.com/MinaProtocol/status/1998755800945181115",
    "fullText": "🗳️ Mesa OCV is live: How to cast your vote! 🗳️\n\n1⃣ Open your preferred Mina wallet\n2⃣ Send a transaction to yourself for each MIP you’d like to vote on: \n\nReceiver address: your own address \nAmount: 0 MINA\nMemo field:\n✅ To vote IN FAVOR: Enter the proposal's exact keyword (e.g.,",
    "formatCreatedAt": "2025-12-10 14:04:52"
  },
  {
    "name": "Monad (mainnet arc)",
    "tweetUrl": "https://x.com/monad/status/1998755001427259779",
    "fullText": "It can pay to fix your attention span \n\nWith @fluffleworld users can earn rewards for locking in \n\nNow available on the app store https://t.co/xaTIKcBUyb",
    "formatCreatedAt": "2025-12-10 14:01:42"
  },
  {
    "name": "Polymarket",
    "tweetUrl": "https://x.com/Polymarket/status/1998754826407260296",
    "fullText": "🚨 NEW POLYMARKET: Will Time's 2025 Person of the Year be leaked?\nhttps://t.co/JqvfgQ1989",
    "formatCreatedAt": "2025-12-10 14:01:00"
  },
  {
    "name": "Polymarket",
    "tweetUrl": "https://x.com/Polymarket/status/1998748788463112524",
    "fullText": "There's a 99% chance Jerome Powell starts today's FOMC press conference with \"Good Afternoon.\" \n\nThe last time he skipped it, the Dow plunged nearly 1,000 points.\n\nWhat could go wrong?\nhttps://t.co/596mXp9FFX",
    "formatCreatedAt": "2025-12-10 13:37:00"
  },
  {
    "name": "Solana",
    "tweetUrl": "https://x.com/solana/status/1998747413952319845",
    "fullText": "Breakpoint mode activated ✅ https://t.co/UQMVx0kiPb",
    "formatCreatedAt": "2025-12-10 13:31:33"
  }
]