[
  {
    "name": "Box",
    "tweetUrl": "https://x.com/BoxMrChen/status/1937799588670550219",
    "fullText": "Yap和抖音带货最大的区别在于\n\n抖音影响力越大，越容易遭到反噬\nYap影响力越大，越容易赚更多钱",
    "formatCreatedAt": "2025-06-25 09:06:39"
  },
  {
    "name": "莫蒂 🐍",
    "tweetUrl": "https://x.com/Morty_happy/status/1937790295179206840",
    "fullText": "开冲了🚀 $HSK https://t.co/VInm2KoXpr",
    "formatCreatedAt": "2025-06-25 08:29:43"
  },
  {
    "name": "0xkevin (🖤 , 💙)",
    "tweetUrl": "https://x.com/0xKevin00/status/1937787647457656997",
    "fullText": "Sui 链隐藏大毛Momentum ：卡塔尔王室大力爆金\n\nSui 生态从年初开始就如火如茶，但是因 cetus 事件瞬间熄火，虽然造成了不小的损失，但好在 Sui 生态只要官方背书过，就不用担心赔不起\n\n这个事件让整个生态的神经开始重新集中在“安全性+性能+流动性”的核心基建之上，恰好让 Momentum https://t.co/kzfAq57rjZ",
    "formatCreatedAt": "2025-06-25 08:19:12"
  }
]