[
  {
    "name": "Polymarket",
    "tweetUrl": "https://x.com/Polymarket/status/1999611623586103334",
    "fullText": "JUST IN: U.S. Treasury plans to put Trump's face on a new $1 coin to be issued next year. https://t.co/L27hjMnSgi",
    "formatCreatedAt": "2025-12-12 22:45:36"
  },
  {
    "name": "Polymarket",
    "tweetUrl": "https://x.com/Polymarket/status/1999610491404943469",
    "fullText": "BREAKING: Elon Musk predicts Steve Bannon will be arrested again, following newly released Epstein Files.",
    "formatCreatedAt": "2025-12-12 22:41:06"
  },
  {
    "name": "Polymarket",
    "tweetUrl": "https://x.com/Polymarket/status/1999596832771486023",
    "fullText": "JUST IN: Despite media rumors, there's only a 5% chance Trump reschedules marijuana this year.\nhttps://t.co/p4TG3Rmcw9",
    "formatCreatedAt": "2025-12-12 21:46:50"
  }
]