[
  {
    "name": "Cos(余弦)😶‍🌫️",
    "tweetUrl": "https://x.com/evilcos/status/1978799124360388776",
    "fullText": "一个签名点击（1click）就可以将用户钱包私钥权限转移走的机制真不是个好机制，这个比私钥泄露还令人难受。",
    "formatCreatedAt": "2025-10-16 12:24:10"
  },
  {
    "name": "allincrypto 熬鹰资本 🇨🇳",
    "tweetUrl": "https://x.com/thankUcrypto/status/1978795572506349770",
    "fullText": "今天ETH的波动基本可以确定是新内幕哥调仓转向导致的，有太多跟单交易了。 同样的上一次james也有这个影响力，直到他自己在推上自爆身份后才失去神力。\n这次的这个内幕哥的神秘感依旧，只要别自爆身份出来拉低自己的神秘感，估计跟随资金永远不缺。",
    "formatCreatedAt": "2025-10-16 12:10:03"
  },
  {
    "name": "Cos(余弦)😶‍🌫️",
    "tweetUrl": "https://x.com/evilcos/status/1978781033559371980",
    "fullText": "绝绝绝大多数加密货币用户不用担心遭遇这种针对弱随机私钥或助记词被破解的问题…你们用的主流开源钱包都不容易有这方面风险，当然如果某组织某机构掌握相关算法 0day，那一切毁灭吧，反正也整整齐齐…",
    "formatCreatedAt": "2025-10-16 11:12:17"
  }
]