[
  {
    "name": "0xkevin (🖤 , 💙) $M| 🐜",
    "tweetUrl": "https://x.com/0xKevin00/status/1951877136551399693",
    "fullText": "想象一下，暑假你们一家三口出门自驾\n\n当你在计划长途旅行的路线时，面对着十几张不同的路线图，吃饭游玩攻略，你的脑子应接不暇\n\n此时，一个 AI 出现，你只需要说帮你规划去新疆最省心的路线，AI 就会为你提供一条最完美的路线\n\n📌这就是 @Infinit_Labs  在做的事情，现在变成了链上\n\n你告诉 AI https://t.co/CsLDP9aL8l",
    "formatCreatedAt": "2025-08-03 05:25:48"
  },
  {
    "name": "莫蒂 🐍",
    "tweetUrl": "https://x.com/Morty_happy/status/1951872468475609322",
    "fullText": "根据我的推文画出我的形象\n@grok",
    "formatCreatedAt": "2025-08-03 05:07:15"
  }
]