[
  {
    "name": "Polymarket",
    "tweetUrl": "https://x.com/Polymarket/status/1985440270754717902",
    "fullText": "BREAKING: Governor of Texas claims he will impose a 100% tariff on anyone moving from NYC to Texas if Mamdani wins.",
    "formatCreatedAt": "2025-11-03 20:13:42"
  },
  {
    "name": "Polymarket",
    "tweetUrl": "https://x.com/Polymarket/status/1985437106395586591",
    "fullText": "Election day is tomorrow.\n\nPolymarket projects Mamdani will defeat Cuomo to become the next Mayor of NYC.\n\n92% chance. https://t.co/5uUrRIW6FS",
    "formatCreatedAt": "2025-11-03 20:01:08"
  },
  {
    "name": "Elon Musk",
    "tweetUrl": "https://x.com/elonmusk/status/1985433270507749664",
    "fullText": "Remember to vote tomorrow in New York!\n\nBear in mind that a vote for Curtis is really a vote for Mumdumi or whatever his name is.\n\nVOTE CUOMO!",
    "formatCreatedAt": "2025-11-03 19:45:53"
  },
  {
    "name": "Solana",
    "tweetUrl": "https://x.com/solana/status/1985429581617152116",
    "fullText": "What are you building today on @solana?",
    "formatCreatedAt": "2025-11-03 19:31:14"
  },
  {
    "name": "Polymarket",
    "tweetUrl": "https://x.com/Polymarket/status/1985427117950070874",
    "fullText": "BREAKING: Final NYC election polls show a tight race.\n\nPolymarket shows a clear Mamdani victory.\n\nWhich do you believe?\nhttps://t.co/AFnLOLpLlj",
    "formatCreatedAt": "2025-11-03 19:21:27"
  },
  {
    "name": "Polymarket",
    "tweetUrl": "https://x.com/Polymarket/status/1985423610995974515",
    "fullText": "BREAKING: Polls show a clear Cuomo victory if Sliwa drops out of the NYC Mayoral Election.\n\n&lt; 1% chance he does.\nhttps://t.co/fHYALjE0oz",
    "formatCreatedAt": "2025-11-03 19:07:30"
  }
]