[
  {
    "name": "Polymarket",
    "tweetUrl": "https://x.com/Polymarket/status/2039971160650121698",
    "fullText": "🚨 NEW POLYMARKET: Will a Chinese company have a #1 AI model by the end of this year? https://t.co/V3ZRK2yxUp",
    "formatCreatedAt": "2026-04-03 07:40:00"
  },
  {
    "name": "Injective 中文 🧬 🥷",
    "tweetUrl": "https://x.com/InjectiveLabsCN/status/2039960983419191800",
    "fullText": "🔥最新消息：Injective 正式发布了实时 USDC 主网升级提案，旨在将 $INJ 打造成实时稳定币基础设施和大规模可编程支付的权威结算层。 https://t.co/0xFDunPBPu",
    "formatCreatedAt": "2026-04-03 06:59:33"
  }
]