[
  {
    "name": "Polymarket",
    "tweetUrl": "https://x.com/Polymarket/status/2026369506923172208",
    "fullText": "BREAKING: U.S. military presence in the Middle East is “among the largest in more than two decades” — WaPo",
    "formatCreatedAt": "2026-02-24 18:51:53"
  },
  {
    "name": "Polymarket",
    "tweetUrl": "https://x.com/Polymarket/status/2026361729194799257",
    "fullText": "NEW POLYMARKET: Who will attend Trump’s State of the Union address tonight?\n\n👉 https://t.co/FuPMApIoaB",
    "formatCreatedAt": "2026-02-24 18:20:58"
  },
  {
    "name": "Polymarket",
    "tweetUrl": "https://x.com/Polymarket/status/2026345884812750976",
    "fullText": "BREAKING: JPMorgan Chase CEO, Jamie Dimon, says he sees parallels to what led to the 2008 financial crisis in America.",
    "formatCreatedAt": "2026-02-24 17:18:01"
  },
  {
    "name": "Polymarket",
    "tweetUrl": "https://x.com/Polymarket/status/2026344019354149214",
    "fullText": "JUST IN: Trump remains a top contender in the 2028 Presidential Election, as VP Vance falls in the odds.  \n\n👉 https://t.co/uL5SByRT39 https://t.co/Ol7VcPLfJM",
    "formatCreatedAt": "2026-02-24 17:10:36"
  },
  {
    "name": "Polymarket",
    "tweetUrl": "https://x.com/Polymarket/status/2026340821545431441",
    "fullText": "BREAKING: CIA releases video in Persian to recruit spies: \"Hello. The Central Intelligence Agency (CIA) can hear your voice and wants to help you.\"\nhttps://t.co/5GReFKhLux",
    "formatCreatedAt": "2026-02-24 16:57:54"
  }
]