[
  {
    "name": "$SOLKID",
    "tweetUrl": "https://x.com/solkidcoin/status/2041124490042655126",
    "fullText": "CLAIM 3,000,000 $SOLKID  🚀 \n\nSTEP 1: RT + Like ❤️ \nSTEP 2: Drop your $SOL wallet\n\nFirst 1500 wallets gets guaranteed airdrop https://t.co/bgG3tUsW71",
    "formatCreatedAt": "2026-04-06 12:02:55"
  },
  {
    "name": "Solar (Solana中文社群)",
    "tweetUrl": "https://x.com/Solana_zh/status/2041123770182652256",
    "fullText": "Solana Foundation 现已成为 x402 Foundation 成员，与 Amazon、American Express、Circle、Cloudflare、Coinbase、Fiserv、Google、Mastercard、Microsoft、Shopify、Stripe、Visa 等机构一起。\n\nx402 协议如今在 @linuxfoundation 拥有一个中立的开源归属。\n\n@solana 是 x402 https://t.co/eW38A7kPE3",
    "formatCreatedAt": "2026-04-06 12:00:03"
  },
  {
    "name": "$YEGGY",
    "tweetUrl": "https://x.com/yeggysol/status/2041122674366173187",
    "fullText": "Claim $450,000 - $YEGGY airdrop for first 4500 🔥 \n\n$YEGGY will list soon on $SOLANA\n\n✅ Follow @yeggysol \n✅ RT + Like\n✅ Comments $SOL address\n\nDistribution airdrop 2 hours ⏳ https://t.co/nG3GMuab6k",
    "formatCreatedAt": "2026-04-06 11:55:42"
  },
  {
    "name": "Polymarket",
    "tweetUrl": "https://x.com/Polymarket/status/2041100602940260611",
    "fullText": "🚨 NEW POLYMARKET: What will Trump say during today’s news conference?",
    "formatCreatedAt": "2026-04-06 10:28:00"
  }
]