[
  {
    "name": "Monad",
    "tweetUrl": "https://x.com/monad/status/2012233176576303352",
    "fullText": "Did you know you can add Monad cards to your Apple wallet?",
    "formatCreatedAt": "2026-01-16 18:39:09"
  },
  {
    "name": "Polymarket",
    "tweetUrl": "https://x.com/Polymarket/status/2012222550172951019",
    "fullText": "BREAKING: Trump considers imposing tariffs on all countries which oppose his acquisition of Greenland.",
    "formatCreatedAt": "2026-01-16 17:56:55"
  },
  {
    "name": "Elon Musk",
    "tweetUrl": "https://x.com/elonmusk/status/2012220031015191016",
    "fullText": "https://t.co/K1Jjk28uPj",
    "formatCreatedAt": "2026-01-16 17:46:55"
  },
  {
    "name": "$WALLY",
    "tweetUrl": "https://x.com/WallyThePlay/status/2012218792794030527",
    "fullText": "CLAIM 400,000 $WALLY \n\nSTEP 1: 💟 &amp; 🔁 + Follow 🔔 \n\nSTEP 2: Drop your $SOL wallet  \n\nFirst 450 wallets gets guaranteed airdrop 👀 \n\n#Solana #SolanaAirdrop https://t.co/95gTTXAJEi",
    "formatCreatedAt": "2026-01-16 17:42:00"
  },
  {
    "name": "Polymarket",
    "tweetUrl": "https://x.com/Polymarket/status/2012212073854361670",
    "fullText": "BREAKING: Troops from France, Germany, Sweden, Finland, Norway, &amp; the Netherlands begin arriving in Greenland.",
    "formatCreatedAt": "2026-01-16 17:15:18"
  },
  {
    "name": "Solana Developers",
    "tweetUrl": "https://x.com/solana_devs/status/2012210294605635647",
    "fullText": "Confidential Transfers on Solana: Workshop https://t.co/VZxiMhSZNy",
    "formatCreatedAt": "2026-01-16 17:08:13"
  },
  {
    "name": "Elon Musk",
    "tweetUrl": "https://x.com/elonmusk/status/2012204998738706743",
    "fullText": "Major security breach\n https://t.co/9TtF8ShRX5",
    "formatCreatedAt": "2026-01-16 16:47:11"
  },
  {
    "name": "Polymarket",
    "tweetUrl": "https://x.com/Polymarket/status/2012202021323989335",
    "fullText": "JUST IN: The median age of U.S. homebuyers hits record high of 59-years-old.",
    "formatCreatedAt": "2026-01-16 16:35:21"
  },
  {
    "name": "Polymarket",
    "tweetUrl": "https://x.com/Polymarket/status/2012200531893133571",
    "fullText": "BREAKING: Trump reportedly to unveil plan in Davos allowing 401(k) use for home down payments.",
    "formatCreatedAt": "2026-01-16 16:29:26"
  }
]