[
  {
    "name": "Polymarket",
    "tweetUrl": "https://x.com/Polymarket/status/2047663657031492030",
    "fullText": "JUST IN: Kremlin announces Putin may travel to Miami for G-20 summit.",
    "formatCreatedAt": "2026-04-24 13:07:14"
  },
  {
    "name": "Solar (Solana中文社群)",
    "tweetUrl": "https://x.com/Solana_zh/status/2047662737895874675",
    "fullText": "Solana 2026年4月生态月会 https://t.co/UG66qa0Hz0",
    "formatCreatedAt": "2026-04-24 13:03:35"
  },
  {
    "name": "OpenBuild",
    "tweetUrl": "https://x.com/OpenBuildxyz/status/2047661809432465609",
    "fullText": "Zama Bounty 101 Workshop https://t.co/zvUJXjkkiT",
    "formatCreatedAt": "2026-04-24 12:59:53"
  },
  {
    "name": "OpenBuild",
    "tweetUrl": "https://x.com/OpenBuildxyz/status/2047660335646302713",
    "fullText": "Zama Bounty 101 Workshop https://t.co/0DJZXtpjKh",
    "formatCreatedAt": "2026-04-24 12:54:02"
  },
  {
    "name": "OpenBuild",
    "tweetUrl": "https://x.com/OpenBuildxyz/status/2047659287372038457",
    "fullText": "Zama Bounty 101 Workshop https://t.co/8w2MyFrYwP",
    "formatCreatedAt": "2026-04-24 12:49:52"
  },
  {
    "name": "Polymarket",
    "tweetUrl": "https://x.com/Polymarket/status/2047658116926345525",
    "fullText": "NEW: Trade school stocks are outperforming college providers as AI fuels fears of a “white-collar job apocalypse”",
    "formatCreatedAt": "2026-04-24 12:45:13"
  },
  {
    "name": "Polymarket",
    "tweetUrl": "https://x.com/Polymarket/status/2047656000417669125",
    "fullText": "JUST IN: Pete Hegseth says the U.S. operation against Iran is “a gift to the world”",
    "formatCreatedAt": "2026-04-24 12:36:48"
  },
  {
    "name": "OpenBuild",
    "tweetUrl": "https://x.com/OpenBuildxyz/status/2047655904758337766",
    "fullText": "Zama Bounty 101 Workshop https://t.co/6NdJ4J6WON",
    "formatCreatedAt": "2026-04-24 12:36:25"
  },
  {
    "name": "OpenBuild",
    "tweetUrl": "https://x.com/OpenBuildxyz/status/2047655645680451655",
    "fullText": "Zama Bounty 101 Workshop https://t.co/8NZmqy4xxz",
    "formatCreatedAt": "2026-04-24 12:35:24"
  },
  {
    "name": "OpenBuild",
    "tweetUrl": "https://x.com/OpenBuildxyz/status/2047655308668043565",
    "fullText": "Zama Bounty 101 Workshop https://t.co/lAhBFyyCuP",
    "formatCreatedAt": "2026-04-24 12:34:03"
  },
  {
    "name": "Polymarket",
    "tweetUrl": "https://x.com/Polymarket/status/2047654301636382729",
    "fullText": "JUST IN: Israeli PM, Netanyahu, announces he was diagnosed with prostate cancer.",
    "formatCreatedAt": "2026-04-24 12:30:03"
  },
  {
    "name": "33357.xyz(samqi)",
    "tweetUrl": "https://x.com/33357xyz/status/2047653142792409309",
    "fullText": "https://t.co/T511WXpEmM",
    "formatCreatedAt": "2026-04-24 12:25:27"
  },
  {
    "name": "OpenBuild",
    "tweetUrl": "https://x.com/OpenBuildxyz/status/2047651685355671810",
    "fullText": "Zama Bounty 101 Workshop https://t.co/msB9jNd5mI",
    "formatCreatedAt": "2026-04-24 12:19:39"
  },
  {
    "name": "OpenBuild",
    "tweetUrl": "https://x.com/OpenBuildxyz/status/2047651268349370508",
    "fullText": "Zama Bounty 101 Workshop https://t.co/SaYcauJMTe",
    "formatCreatedAt": "2026-04-24 12:18:00"
  },
  {
    "name": "OpenBuild",
    "tweetUrl": "https://x.com/OpenBuildxyz/status/2047650382416118061",
    "fullText": "Zama Bounty 101 Workshop https://t.co/av93HYhB8q",
    "formatCreatedAt": "2026-04-24 12:14:29"
  },
  {
    "name": "$BEAST",
    "tweetUrl": "https://x.com/iBeastSolCoin/status/2047649249068773401",
    "fullText": "$BEAST Airdrop is open for 12 Hours 🪂\n\nDrop your #Solana Wallet Below, Follow 🔔 &amp; RT 👇\n\nEvery Wallet gets 100.000.000 $BEAST 🥛\n\nCheck Your wallet in 12 hours ⏰ https://t.co/KbhzTR5JJq",
    "formatCreatedAt": "2026-04-24 12:09:59"
  },
  {
    "name": "$BEAST",
    "tweetUrl": "https://x.com/iBeastSolCoin/status/2047649193959752188",
    "fullText": "Don't ask why,\n\nJust drop your Solana $SOL address &amp; RT ♻️\n\nEvery wallet gets 50,000 $BEAST 🪂\n\nFirst 500 wallets ⬇️⬇️ https://t.co/5VS8GpBZcs",
    "formatCreatedAt": "2026-04-24 12:09:45"
  },
  {
    "name": "$BEAST",
    "tweetUrl": "https://x.com/iBeastSolCoin/status/2047649026170884146",
    "fullText": "CLAIM 3,000,000 $BEAST \n\nSTEP 1: 💟 &amp; 🔁 + Follow\n\nSTEP 2: Drop your $SOL wallet\n\nFirst 1500 wallets gets guaranteed airdrop ⏰ https://t.co/UZl3TlhC49",
    "formatCreatedAt": "2026-04-24 12:09:05"
  },
  {
    "name": "OpenBuild",
    "tweetUrl": "https://x.com/OpenBuildxyz/status/2047647079737274537",
    "fullText": "Zama Bounty 101 Workshop https://t.co/W1ORKgXVqK",
    "formatCreatedAt": "2026-04-24 12:01:21"
  },
  {
    "name": "OpenBuild",
    "tweetUrl": "https://x.com/OpenBuildxyz/status/2047646487492821382",
    "fullText": "Zama Bounty 101 Workshop https://t.co/X8w9k0W0pK",
    "formatCreatedAt": "2026-04-24 11:59:00"
  },
  {
    "name": "OpenBuild",
    "tweetUrl": "https://x.com/OpenBuildxyz/status/2047646058860442107",
    "fullText": "Zama Bounty 101 Workshop https://t.co/ixsV0dfgxB",
    "formatCreatedAt": "2026-04-24 11:57:18"
  },
  {
    "name": "Polymarket",
    "tweetUrl": "https://x.com/Polymarket/status/2047643214123803056",
    "fullText": "🚨 NEW POLYMARKET: Diddy released from custody? https://t.co/txFiCgeyaD",
    "formatCreatedAt": "2026-04-24 11:46:00"
  },
  {
    "name": "$FOGO",
    "tweetUrl": "https://x.com/FogoonSol/status/2047637657329533380",
    "fullText": "Claim $500,000 - $FOGO  airdrop for first 2000 🔥 \n\n$FOGO will list April 26th at 14:00 UTC on $SOLANA\n\n✅ Follow @FogoonSol \n✅ RT + Like\n✅ Comments $SOL address\n\nDistribution airdrop april 26th ⏳ https://t.co/WkSMvznkFA",
    "formatCreatedAt": "2026-04-24 11:23:55"
  }
]