[
  {
    "name": "pseudo 🇺🇦",
    "tweetUrl": "https://x.com/pseudotheos/status/2034681216184533330",
    "fullText": "https://t.co/zacAdAotX5",
    "formatCreatedAt": "2026-03-19 17:19:39"
  },
  {
    "name": "Polymarket",
    "tweetUrl": "https://x.com/Polymarket/status/2034681190058271207",
    "fullText": "JUST IN: Netanyahu to hold press conference at 2:30pm ET.",
    "formatCreatedAt": "2026-03-19 17:19:32"
  },
  {
    "name": "Polymarket",
    "tweetUrl": "https://x.com/Polymarket/status/2034671066820354547",
    "fullText": "JUST IN: Trump assures the Iran \"excursion\" will be over soon.",
    "formatCreatedAt": "2026-03-19 16:39:19"
  },
  {
    "name": "Polymarket",
    "tweetUrl": "https://x.com/Polymarket/status/2034668275007656311",
    "fullText": "🚨 NEW POLYMARKET: Kanye's \"BULLY\" first week album sales?\nhttps://t.co/iaLlXWXPXL",
    "formatCreatedAt": "2026-03-19 16:28:13"
  },
  {
    "name": "Colosseum",
    "tweetUrl": "https://x.com/colosseum/status/2034666123577442394",
    "fullText": "1/ Announcing the winners of the @Solana Agent Hackathon! 🤖\n\n1st ($50,000) Prize | @DegenDomeSolana\n2nd ($30,000) Prize | AgentOS by @0xbraindeds\n3rd ($15,000) Prize | @blockhelix\n4th ($5,000) Most Agentic Prize | @cludebot https://t.co/KMDqgPW5hs",
    "formatCreatedAt": "2026-03-19 16:19:40"
  },
  {
    "name": "Polymarket",
    "tweetUrl": "https://x.com/Polymarket/status/2034662037968621884",
    "fullText": "JUST IN: UK demands 4chan pay fine for not complying with age verification laws, lawyer responds with revolutionary war rant &amp; image of giant hamster dressed as Godzilla.",
    "formatCreatedAt": "2026-03-19 16:03:26"
  },
  {
    "name": "Polymarket",
    "tweetUrl": "https://x.com/Polymarket/status/2034657741415817383",
    "fullText": "BREAKING: CBS launches investigation into alleged fraud at Los Angeles office plaza that hosts 89 hospice companies.",
    "formatCreatedAt": "2026-03-19 15:46:22"
  },
  {
    "name": "Polymarket",
    "tweetUrl": "https://x.com/Polymarket/status/2034656211048513672",
    "fullText": "BREAKING: Insurance premiums on a $100 million ship traveling through Hormuz soar to ~$5 million.",
    "formatCreatedAt": "2026-03-19 15:40:17"
  },
  {
    "name": "Polymarket",
    "tweetUrl": "https://x.com/Polymarket/status/2034654927981519104",
    "fullText": "🚨 NEW POLYMARKET: What will Trump say during events with Japanese Prime Minster? https://t.co/eE3gNcsGnw",
    "formatCreatedAt": "2026-03-19 15:35:11"
  }
]