[
  {
    "name": "$RIPPIN",
    "tweetUrl": "https://x.com/rippinxsol/status/2036700551682117782",
    "fullText": "CLAIM 500,000 $RIPPIN\n\nSTEP 1 : 💟 &amp; 🔁 + Follow 🔔 \n\nSTEP 2 : Drop your $SOL wallet\n\nFirst 222 wallets gets guaranteed airdrop 👀\n\n#Solana #SolanaAirdrop https://t.co/VMQ5QX6d8i",
    "formatCreatedAt": "2026-03-25 07:03:46"
  },
  {
    "name": "Elon Musk",
    "tweetUrl": "https://x.com/elonmusk/status/2036693879270064369",
    "fullText": "The next @Grok Imagine release will be epic. \n\nWe are doubling down.",
    "formatCreatedAt": "2026-03-25 06:37:15"
  }
]