[
  {
    "name": "Polymarket",
    "tweetUrl": "https://x.com/Polymarket/status/2028505741347197389",
    "fullText": "🚨 NEW POLYMARKET: Trump announces end of military operations by…?\nhttps://t.co/X3pFl58D47",
    "formatCreatedAt": "2026-03-02 16:20:31"
  },
  {
    "name": "Donald J. Trump",
    "tweetUrl": "https://x.com/realDonaldTrump/status/2028505632123326484",
    "fullText": "https://t.co/uAxTGrJisv",
    "formatCreatedAt": "2026-03-02 16:20:05"
  },
  {
    "name": "Elon Musk",
    "tweetUrl": "https://x.com/elonmusk/status/2028500984977330453",
    "fullText": "Expanding to the stars avoids risk of a mouse utopian behavioral sink",
    "formatCreatedAt": "2026-03-02 16:01:37"
  },
  {
    "name": "allincrypto 熬鹰资本 🇨🇳",
    "tweetUrl": "https://x.com/thankUcrypto/status/2028496179303170451",
    "fullText": "我是破了2000才开始追的，如果是大级别主升浪，就不算差。\n总共就40WU了，5X拉满，希望惊喜会来吧。 https://t.co/AeaEEGP9D3",
    "formatCreatedAt": "2026-03-02 15:42:31"
  },
  {
    "name": "allincrypto 熬鹰资本 🇨🇳",
    "tweetUrl": "https://x.com/thankUcrypto/status/2028494777139040337",
    "fullText": "不追就上不去车的感觉，多久没出现了。",
    "formatCreatedAt": "2026-03-02 15:36:57"
  },
  {
    "name": "allincrypto 熬鹰资本 🇨🇳",
    "tweetUrl": "https://x.com/thankUcrypto/status/2028486419187163509",
    "fullText": "XAU到顶了。\n疑似伊朗核设施被导弹完全捣毁，没有秘密武器反扑了。",
    "formatCreatedAt": "2026-03-02 15:03:44"
  },
  {
    "name": "Polymarket",
    "tweetUrl": "https://x.com/Polymarket/status/2028480989366751686",
    "fullText": "BREAKING: France declares it's increasing its nuclear arsenal.",
    "formatCreatedAt": "2026-03-02 14:42:09"
  }
]