[
  {
    "name": "Polymarket",
    "tweetUrl": "https://x.com/Polymarket/status/2043642099615342592",
    "fullText": "BREAKING: Pistachio prices surge to an eight-year high amid supply disruptions in Iran.",
    "formatCreatedAt": "2026-04-13 10:47:00"
  },
  {
    "name": "HOH水分子",
    "tweetUrl": "https://x.com/0xHOH/status/2043627038373003572",
    "fullText": "👀 深圳的水家人们，这个周末有什么安排呢？ \n来点不一样的吧！#Sui Dev Meetup 就等你来\n\n✨ MystenLabs 联创重磅加盟\n✨ 技术干货 + 生态前瞻\n✨ 与一线开发者、生态核心角色面对面\n\n📅 4月18日 14:00\n📍 深圳 · 南山 · 前海\n🎟️ 报名后获取详细活动地址\nhttps://t.co/tTt0KRs6FF",
    "formatCreatedAt": "2026-04-13 09:47:09"
  },
  {
    "name": "Polymarket",
    "tweetUrl": "https://x.com/Polymarket/status/2043616179244474810",
    "fullText": "🚨 NEW POLYMARKET: Where will the next US-Iran diplomatic meeting happen? https://t.co/QCo4wAnSw0",
    "formatCreatedAt": "2026-04-13 09:04:00"
  },
  {
    "name": "allincrypto 熬鹰资本 🇨🇳",
    "tweetUrl": "https://x.com/thankUcrypto/status/2043615969567014949",
    "fullText": "多少做市商找我合作我一个都没接过。\n因为我知道一个市场最顶级的币一定是天时地利人和都占的。\n控盘99%的币还少吗？但是大多都坚持不了多久昨天涨今天就跌了。",
    "formatCreatedAt": "2026-04-13 09:03:10"
  }
]