[
  {
    "name": "Solar (Solana中文社群)",
    "tweetUrl": "https://x.com/Solana_zh/status/2050525064118821152",
    "fullText": "Solar Mini Hacker House Singapore @021Labxyz 圆满收官🎉\n\n高强度从早到晚的一天，共有 25 支团队进行了 Demo，在短短几天内完成的项目质量让我们感到惊喜！恭喜前十名项目获得城市奖池 $1,500，并推荐进入Solar $12,500华语奖池\n\n🥇第 1 名 $500 Manic @robinn_eth\n🥈第 2 名 $300 Mystablecorp https://t.co/2A770frOoA",
    "formatCreatedAt": "2026-05-02 10:37:26"
  },
  {
    "name": "Polymarket",
    "tweetUrl": "https://x.com/Polymarket/status/2050520584572793251",
    "fullText": "JUST IN: Spirit Airlines has shutdown all operations — all flights cancelled, no more customer support.",
    "formatCreatedAt": "2026-05-02 10:19:38"
  },
  {
    "name": "Polymarket",
    "tweetUrl": "https://x.com/Polymarket/status/2050520170817589425",
    "fullText": "JUST IN: Trump imposes sanctions on top Cuban officials “complicit in government corruption or serious human rights violations”",
    "formatCreatedAt": "2026-05-02 10:18:00"
  },
  {
    "name": "Polymarket",
    "tweetUrl": "https://x.com/Polymarket/status/2050506077993886175",
    "fullText": "🚨 NEW POLYMARKET: Iran closes its airspace by…? https://t.co/TKVlTAu08i",
    "formatCreatedAt": "2026-05-02 09:22:00"
  }
]