[
  {
    "name": "Polymarket",
    "tweetUrl": "https://x.com/Polymarket/status/2032793616108945841",
    "fullText": "JUST IN: Uber founder says AI will make human labor far more valuable, predicts plumbers could become “like LeBron” in an automated world.",
    "formatCreatedAt": "2026-03-14 12:19:00"
  },
  {
    "name": "Polymarket",
    "tweetUrl": "https://x.com/Polymarket/status/2032785814883815721",
    "fullText": "JUST IN: Uber founder Travis Kalanick plans to launch new AI &amp; robotics company.",
    "formatCreatedAt": "2026-03-14 11:48:00"
  },
  {
    "name": "Solana",
    "tweetUrl": "https://x.com/solana/status/2032778349798678840",
    "fullText": "https://t.co/KkmBdisoIq",
    "formatCreatedAt": "2026-03-14 11:18:20"
  }
]