[
  {
    "name": "HackQuest",
    "tweetUrl": "https://x.com/HackQuest_/status/2037132416725508516",
    "fullText": "0G APAC Hackathon AMA#1 https://t.co/tJTdqS7JQK",
    "formatCreatedAt": "2026-03-26 11:39:50"
  },
  {
    "name": "0xkevin (🖤 , 💙)",
    "tweetUrl": "https://x.com/0xKevin00/status/2037122318015848609",
    "fullText": "&lt;The book of Elon&gt; 围绕马斯克的新书，昨天刚发布\n\n作者花费5年时间整理了老马从濒临破产到世界钢铁侠的300万字素材\n\n这本书被称为&lt;创业者唯一需要的书&gt;，售价200块，我买了电子版免费分享👇\n\n链接:https://t.co/KmLFPkZSqV?\n提取码:elon\n\n买了同名 勿跟：0xf05079a10eb434d6480d9eb9362c2d29d6774444 https://t.co/PYk93Us6om",
    "formatCreatedAt": "2026-03-26 10:59:43"
  },
  {
    "name": "Solana",
    "tweetUrl": "https://x.com/solana/status/2037121183230185632",
    "fullText": "Taking note of everyone who presses this button https://t.co/CJm8RS8GjG",
    "formatCreatedAt": "2026-03-26 10:55:12"
  },
  {
    "name": "allincrypto 熬鹰资本 🇨🇳",
    "tweetUrl": "https://x.com/thankUcrypto/status/2037108499793289583",
    "fullText": "这周就siren ETH赚了钱的，Tao和币安人生都是小赚跑的。\n\n其实这周说是震荡，实际就是纯消息面驱动的行情，甚至每次拉升 回调都是有迹可循的。",
    "formatCreatedAt": "2026-03-26 10:04:48"
  }
]