[
  {
    "name": "Polymarket",
    "tweetUrl": "https://x.com/Polymarket/status/2006835234831270307",
    "fullText": "BREAKING: Elon Musk now projected to be the world’s first trillionaire this year.\n\n60% chance.\nhttps://t.co/91pR1Mz0ez",
    "formatCreatedAt": "2026-01-01 21:09:39"
  },
  {
    "name": "$VEXON",
    "tweetUrl": "https://x.com/VexonXtoken/status/2006832986302591115",
    "fullText": "We are launching tomorrow at 15:00 UTC ! 🚀\n\n$VEXON is a decentralized token built on #Solana\n\nFirst 1,500 Address will get 100,000,000 $VEXON\n\nAirdrop open 🪂 Drop your $SOL address &amp; RT ♻️\n\nSnapshots 12 hours ⏳ https://t.co/czuCJKZC75",
    "formatCreatedAt": "2026-01-01 21:00:43"
  },
  {
    "name": "Polymarket",
    "tweetUrl": "https://x.com/Polymarket/status/2006827420020875502",
    "fullText": "JUST IN: It has been revealed Elon Musk paid so much in taxes one year that it broke the IRS’s computer.",
    "formatCreatedAt": "2026-01-01 20:38:36"
  },
  {
    "name": "SALARY",
    "tweetUrl": "https://x.com/SalaryXCoin/status/2006825085487952054",
    "fullText": "Claim $400,000 - $SALARY airdrop for first 4444 🔥 \n\n$SALARY will list Today at 14:00 UTC on $Solana \n\n✅Follow @SalaryXCoin \n✅RT + Like + Telegram https://t.co/OdjhfxIIaW \n✅Comments $SOL address\n\nDistribution airdrop in 12 hours ⏳\n#SolanaAirdrop https://t.co/9mcpwLR6uL",
    "formatCreatedAt": "2026-01-01 20:29:20"
  },
  {
    "name": "$VEXON",
    "tweetUrl": "https://x.com/VexonXtoken/status/2006809681365479650",
    "fullText": "Giveaway - 4,000,000 $VEXON 🎁 \n\nTo participate:\n- Follow @VexonXtoken \n- Like + RT \n- Comment your $SOL address\n\nGiveaway ends 2 January ⏳ https://t.co/pOw3sBALgX",
    "formatCreatedAt": "2026-01-01 19:28:07"
  }
]