[
  {
    "name": "Polymarket",
    "tweetUrl": "https://x.com/Polymarket/status/2035782875983835168",
    "fullText": "BREAKING: Iran begins collecting $2 million in transit fees per vessel for ships passing through the Strait of Hormuz.",
    "formatCreatedAt": "2026-03-22 18:17:15"
  },
  {
    "name": "Polymarket",
    "tweetUrl": "https://x.com/Polymarket/status/2035765834006528386",
    "fullText": "JUST IN: Border czar Tom Homan says ICE will only do “non-significant tasks” at airports.",
    "formatCreatedAt": "2026-03-22 17:09:32"
  }
]